MANIFEST.in
README.rst
requirements.txt
setup.py
LICENSES/.DS_Store
LICENSES/CESIUM_LICENSE.md
cesiumpy/__init__.py
cesiumpy/base.py
cesiumpy/camera.py
cesiumpy/common.py
cesiumpy/constants.py
cesiumpy/datasource.py
cesiumpy/provider.py
cesiumpy/scene.py
cesiumpy/testing.py
cesiumpy/version.py
cesiumpy/viewer.py
cesiumpy/widget.py
cesiumpy.egg-info/PKG-INFO
cesiumpy.egg-info/SOURCES.txt
cesiumpy.egg-info/dependency_links.txt
cesiumpy.egg-info/requires.txt
cesiumpy.egg-info/top_level.txt
cesiumpy/data/__init__.py
cesiumpy/data/country.py
cesiumpy/data/countries/bower.json
cesiumpy/data/countries/composer.json
cesiumpy/data/countries/countries.json
cesiumpy/data/countries/package.json
cesiumpy/data/countries/data/abw.geo.json
cesiumpy/data/countries/data/abw.svg
cesiumpy/data/countries/data/afg.geo.json
cesiumpy/data/countries/data/afg.svg
cesiumpy/data/countries/data/ago.geo.json
cesiumpy/data/countries/data/ago.svg
cesiumpy/data/countries/data/aia.geo.json
cesiumpy/data/countries/data/aia.svg
cesiumpy/data/countries/data/ala.geo.json
cesiumpy/data/countries/data/ala.svg
cesiumpy/data/countries/data/alb.geo.json
cesiumpy/data/countries/data/alb.svg
cesiumpy/data/countries/data/and.geo.json
cesiumpy/data/countries/data/and.svg
cesiumpy/data/countries/data/are.geo.json
cesiumpy/data/countries/data/are.svg
cesiumpy/data/countries/data/arg.geo.json
cesiumpy/data/countries/data/arg.svg
cesiumpy/data/countries/data/arm.geo.json
cesiumpy/data/countries/data/arm.svg
cesiumpy/data/countries/data/asm.geo.json
cesiumpy/data/countries/data/asm.svg
cesiumpy/data/countries/data/ata.geo.json
cesiumpy/data/countries/data/ata.svg
cesiumpy/data/countries/data/atf.geo.json
cesiumpy/data/countries/data/atf.svg
cesiumpy/data/countries/data/atg.geo.json
cesiumpy/data/countries/data/atg.svg
cesiumpy/data/countries/data/aus.geo.json
cesiumpy/data/countries/data/aus.svg
cesiumpy/data/countries/data/aut.geo.json
cesiumpy/data/countries/data/aut.svg
cesiumpy/data/countries/data/aze.geo.json
cesiumpy/data/countries/data/aze.svg
cesiumpy/data/countries/data/bdi.geo.json
cesiumpy/data/countries/data/bdi.svg
cesiumpy/data/countries/data/bel.geo.json
