Metadata-Version: 1.0
Name: cesiumpy
Version: 0.3.2
Summary: python wrapper of cesium.js for 3D geospatial visualization
Home-page: http://cesiumpy.readthedocs.org/en/stable
Author: sinhrks
Author-email: sinhrks@gmail.com
License: Apache 2.0
Platform: UNKNOWN
